{
  "@context": "https://schema.org",
  "@type": "Restaurant",
  "name": "PalachinqO",
  "url": "https://palachinqo.hr/",
  "telephone": "+385924610263",
  "servesCuisine": ["Palačinke", "Crepes"],
  "priceRange": "€",
  "openingHoursSpecification": [
    {
      "@type": "OpeningHoursSpecification",
      "dayOfWeek": ["Tuesday","Wednesday","Thursday","Friday","Saturday","Sunday"],
      "opens": "17:00",
      "closes": "23:00"
    }
  ],
  "address": {
    "@type": "PostalAddress",
    "streetAddress": "Ilica 75",
    "addressLocality": "Zagreb",
    "postalCode": "10000",
    "addressCountry": "HR"
  },
  "geo": {
    "@type": "GeoCoordinates",
    "latitude": 45.8124,
    "longitude": 15.9619
  }
}
